README.rst
setup.py
nose_easy_init/__init__.py
nose_easy_init/plugin.py
nose_easy_init.egg-info/PKG-INFO
nose_easy_init.egg-info/SOURCES.txt
nose_easy_init.egg-info/dependency_links.txt
nose_easy_init.egg-info/entry_points.txt
nose_easy_init.egg-info/top_level.txt