Metadata-Version: 1.1
Name: nose-easy-init
Version: 1.0.2
Summary: A plugin for nose to easily specify an initialization  script
Home-page: https://github.com/sprin/nose-easy-init
Author: sprin
Author-email: sprin.pypi@fastmail.net
License: UNKNOWN
Download-URL: https://github.com/sprin/nose-easy-init/tarball/1.0.2
Platform: UNKNOWN
